hitools/__init__.py
hitools/functools.py
hitools/logging.py
hitools-0.0.3.dist-info/LICENSE
hitools-0.0.3.dist-info/METADATA
hitools-0.0.3.dist-info/WHEEL
hitools-0.0.3.dist-info/top_level.txt
hitools-0.0.3.dist-info/RECORD
